tests/__init__.py
tests/test_gmod.py
tests/test_gmodpath.py
tests/test_locations.py
tests/test_vis.py
tests/test_vis_versions.py
tests/testdata.py
vista_sdk/Client.py
vista_sdk/Gmod.py
vista_sdk/GmodDto.py
vista_sdk/GmodNode.py
vista_sdk/GmodPath.py
vista_sdk/GmodVersioningDto.py
vista_sdk/LocationBuilder.py
vista_sdk/LocationSetsVisitor.py
vista_sdk/Locations.py
vista_sdk/LocationsDto.py
vista_sdk/ParsingErrors.py
vista_sdk/TraversalHandlerResult.py
vista_sdk/VIS.py
vista_sdk/VisVersions.py
vista_sdk/__init__.py
vista_sdk/internal/ChdDictionary.py
vista_sdk/internal/LocationParsingErrorBuilder.py
vista_sdk/internal/__init__.py
vista_sdk-17.dist-info/LICENSE
vista_sdk-17.dist-info/METADATA
vista_sdk-17.dist-info/WHEEL
vista_sdk-17.dist-info/top_level.txt
vista_sdk-17.dist-info/RECORD
