Metadata-Version: 2.1
Name: vista-sdk
Version: 17
Summary: SDKs and tools relating to DNVs Vessel Information Structure (VIS), ISO 19847, ISO 19848 standards
Home-page: https://github.com/dnv-opensource/vista-sdk
Author: Anders Fredriksen
Author-email: anders.fredriksen@dnv.com
License: MIT
Classifier: Programming Language :: Python :: 3
Classifier: License :: OSI Approved :: MIT License
Classifier: Operating System :: OS Independent
Requires-Python: >=3.8
License-File: LICENSE
